LBBNorm/__init__.py
LBBNorm/adaptive_color_deconvolution.py
LBBNorm/macenko.py
LBBNorm/modified_reinhard.py
LBBNorm/reinhard.py
LBBNorm/slide_patcher.py
LBBNorm/vahadane.py
LBBNorm-3.3.6.dist-info/METADATA
LBBNorm-3.3.6.dist-info/WHEEL
LBBNorm-3.3.6.dist-info/top_level.txt
LBBNorm-3.3.6.dist-info/RECORD
