Metadata-Version: 2.1
Name: LBBNorm
Version: 3.3.6
Summary: This is a description!
Author: Laboratory of Systems Biology and Bioinformatics (LBB)
Author-email: amasoudin@ut.ac.ir
License: MIT
Keywords: Healthcare Bio-Informatics
Classifier: Development Status :: 4 - Beta
Classifier: Intended Audience :: Science/Research
Classifier: Intended Audience :: Healthcare Industry
Classifier: Intended Audience :: Information Technology
Classifier: Topic :: Scientific/Engineering :: Bio-Informatics
Classifier: Topic :: Scientific/Engineering :: Medical Science Apps.
Classifier: Topic :: Scientific/Engineering :: Image Recognition
Classifier: Programming Language :: Python :: 3
Classifier: Programming Language :: Python :: 3.8
Classifier: Programming Language :: Python :: 3.9
Classifier: Programming Language :: Python :: 3.10
Classifier: Operating System :: OS Independent
Requires-Dist: numpy
Requires-Dist: tensorflow
Requires-Dist: opencv-python
Requires-Dist: spams
